methodwebscan/__init__.py
methodwebscan/core/__init__.py
methodwebscan/core/datetime_utils.py
methodwebscan/core/enum.py
methodwebscan/core/pydantic_utilities.py
methodwebscan/core/serialization.py
methodwebscan/py.typed
methodwebscan/resources/__init__.py
methodwebscan/resources/common/__init__.py
methodwebscan/resources/common/resources/__init__.py
methodwebscan/resources/common/resources/config/__init__.py
methodwebscan/resources/common/resources/config/send_http_request_config.py
methodwebscan/resources/common/resources/http/__init__.py
methodwebscan/resources/common/resources/http/binary_body.py
methodwebscan/resources/common/resources/http/body.py
methodwebscan/resources/common/resources/http/form_body.py
methodwebscan/resources/common/resources/http/http_method.py
methodwebscan/resources/common/resources/http/http_request.py
methodwebscan/resources/common/resources/http/http_request_params.py
methodwebscan/resources/common/resources/http/http_request_response.py
methodwebscan/resources/common/resources/http/http_response.py
methodwebscan/resources/common/resources/http/json_body.py
methodwebscan/resources/common/resources/http/multipart_body.py
methodwebscan/resources/common/resources/http/multipart_part.py
methodwebscan/resources/common/resources/http/text_body.py
methodwebscan/resources/common/resources/http/web_protocol.py
methodwebscan/resources/common/resources/method/__init__.py
methodwebscan/resources/common/resources/method/browserbase_request_config.py
methodwebscan/resources/common/resources/method/browserbase_request_secrets.py
methodwebscan/resources/common/resources/method/headless_request_config.py
methodwebscan/resources/common/resources/method/request_method.py
methodwebscan/resources/common/resources/nuclei/__init__.py
methodwebscan/resources/common/resources/nuclei/resources/__init__.py
methodwebscan/resources/common/resources/nuclei/resources/config/__init__.py
methodwebscan-0.0.205.dist-info/METADATA
methodwebscan-0.0.205.dist-info/WHEEL
methodwebscan-0.0.205.dist-info/RECORD
